sim_dist/__init__.py
sim_dist/data.py
sim_dist/replicate.py
sim_dist/topo.py
sim_dist/models/__init__.py
sim_dist/models/wrn.py
sim_dist_train-0.0.8.dist-info/METADATA
sim_dist_train-0.0.8.dist-info/WHEEL
sim_dist_train-0.0.8.dist-info/top_level.txt
sim_dist_train-0.0.8.dist-info/RECORD
